mock_chroot/__init__.py
mock_chroot/config/__init__.py
mock_chroot/config/builder.py
mock_chroot/config/composition.py
mock_chroot/config/highlevel.py
mock_chroot/config/koji.py
mock_chroot-0.0.1.dev4.dist-info/DESCRIPTION.rst
mock_chroot-0.0.1.dev4.dist-info/METADATA
mock_chroot-0.0.1.dev4.dist-info/RECORD
mock_chroot-0.0.1.dev4.dist-info/WHEEL
mock_chroot-0.0.1.dev4.dist-info/metadata.json
mock_chroot-0.0.1.dev4.dist-info/pbr.json
mock_chroot-0.0.1.dev4.dist-info/top_level.txt
