Metadata-Version: 2.0
Name: mock-chroot
Version: 0.0.1.dev4
Summary: Python library for using the Mock chroot-based build tool
Home-page: https://github.com/ifireball/python-mockchroot
Author: Barak Korren
Author-email: bkorren@redhat.com
License: 'MIT'
Keywords: development
